{
  "holder": {
    "type": "jobsplus:job",
    "id": "jobsplus:farmer"
  },
  "type": "arc:on_plant_crop",
  "short_description": "Plant a crop",
  "description": "Planting crops is a crucial part of being a Farmer. With every seed you plant, you'll get a chance to earn job experience points. While planting crops isn't as rewarding as harvesting them, it's still an essential task that can help you progress in your career.",
  "rewards": [
    {
      "type": "jobsplus:job_exp",
      "min": 0,
      "max": 1
    }
  ]
}